nctools/__init__.py
nctools/__main__.py
nctools/main.py
nctools/nccalc.py
nctools/ncdump.py
nctools/ncplot.py
nctools/ncread.py
nctools/ncutil.py
tests/__init__.py
tests/test_nccalc.py
tests/test_ncdump.py
tests/test_ncplot.py
tests/test_ncread.py
nctools-0.1.23.dist-info/LICENSE
nctools-0.1.23.dist-info/METADATA
nctools-0.1.23.dist-info/WHEEL
nctools-0.1.23.dist-info/entry_points.txt
nctools-0.1.23.dist-info/top_level.txt
nctools-0.1.23.dist-info/RECORD
